Workbook

Sheet Assumptions
A1: ACQUIRER — Infosys Limited
A2: Share price (₹) | B2: 1047.2
A3: Shares outstanding (Cr) | B3: 404.89279
A4: Net income TTM (₹ Cr) | B4: 30569.406
A5: Revenue TTM (₹ Cr) | B5: 186000.02
A6: EBITDA TTM (₹ Cr) | B6: 40857.633
A7: Total debt (₹ Cr) | B7: 8922.6127
A8: Cash (₹ Cr) | B8: 34195.658
A9: Book value (₹ Cr) | B9: 8554566.5
A10: TARGET — Persistent Systems Limited
A11: Undisturbed price (₹) | B11: 4682.7
A12: Diluted shares (Cr) | B12: 15.623104
A13: Net income TTM (₹ Cr) | B13: 1865.1199
A14: Revenue TTM (₹ Cr) | B14: 14748.449
A15: EBITDA TTM (₹ Cr) | B15: 2616.0529
A16: Total debt (₹ Cr) | B16: 477.44799
A17: Book value (₹ Cr) | B17: 7827.0347
A18: DEAL TERMS
A19: Offer price (₹) | B19: 5525.59
A20: Negotiated stake % | B20: 1
A21: % cash consideration | B21: 0.4
A22: % stock consideration | B22: 0.6
A23: % of cash needs from new debt | B23: 0.5
A24: New debt interest rate | B24: 0.085
A25: Cash yield foregone | B25: 0.06
A26: Run-rate synergies (₹ Cr) | B26: 400
A27: Synergy phase-in Y1 | B27: 0.5
A28: Synergy phase-in Y2 | B28: 0.75
A29: Synergy phase-in Y3 | B29: 1
A30: Integration costs Y1 (₹ Cr) | B30: 200
... A36: Open-offer acceptance assumption | B36: 1
A37: CONVENTION
A38: Blue font = hardcoded input. All other tabs are formulas.

Sheet Sources & Uses
A1: ₹ Cr | B1: 0% acceptance | C1: 50% acceptance | D1: 100% acceptance
A2: Equity purchase (negotiated) | B2: =Assumptions!$B$19*Assumptions!$B$12*Assumptions!$B$20 | C2: =Assumptions!$B$19*Assumptions!$B$12*Assumptions!$B$20 | D2: =Assumptions!$B$19*Assumptions!$B$12*Assumptions!$B$20
A3: Open offer consideration | B3: =26%*Assumptions!$B$12*Assumptions!$B$19*0.0 | C3: =26%*Assumptions!$B$12*Assumptions!$B$19*0.5 | D3: =26%*Assumptions!$B$12*Assumptions!$B$19*1.0
A4: Refinance target debt | B4: =Assumptions!$B$16*0 | C4: =Assumptions!$B$16*0 | D4: =Assumptions!$B$16*0
A5: Transaction fees | B5: =Assumptions!$B$34*(B2+B3) | C5: =Assumptions!$B$34*(C2+C3) | D5: =Assumptions!$B$34*(D2+D3)
A6: TOTAL USES | B6: =SUM(B2:B5) | C6: =SUM(C2:C5) | D6: =SUM(D2:D5)
A7: New acquirer stock | B7: =Assumptions!$B$22*B2 | C7: =Assumptions!$B$22*C2 | D7: =Assumptions!$B$22*D2
A8: New bank debt | B8: =Assumptions!$B$23*(Assumptions!$B$21*B2+B3+B4+B5) | C8: =Assumptions!$B$23*(Assumptions!$B$21*C2+C3+C4+C5) | D8: =Assumptions!$B$23*(Assumptions!$B$21*D2+D3+D4+D5)
A9: Balance-sheet cash | B9: =(Assumptions!$B$21*B2+B3+B4+B5)-B8 | C9: =(Assumptions!$B$21*C2+C3+C4+C5)-C8 | D9: =(Assumptions!$B$21*D2+D3+D4+D5)-D8
A10: TOTAL SOURCES | B10: =SUM(B7:B9) | C10: =SUM(C7:C9) | D10: =SUM(D7:D9)
A11: Balance check (must be 0) | B11: =B10-B6 | C11: =C10-C6 | D11: =D10-D6
A12: New shares issued (Cr) | B12: =B7/Assumptions!$B$2 | C12: =C7/Assumptions!$B$2 | D12: =D7/Assumptions!$B$2

Sheet PPA
A1: Item | B1: ₹ Cr
A2: Equity invested (negotiated + open offer) | B2: ='Sources & Uses'!D2+'Sources & Uses'!D3
A3: Owned share of target book value | B3: =(Assumptions!$B$20+26%*Assumptions!$B$36)*Assumptions!$B$17
A4: Excess over book | B4: =B2-B3
A5: Intangible write-up | B5: =MAX(0,Assumptions!$B$31*B4)
A6: Deferred tax liability | B6: =Assumptions!$B$33*B5
A7: Goodwill | B7: =B4-B5+B6
A8: Incremental D&A per year | B8: =B5/Assumptions!$B$32

Sheet Pro-Forma P&L
A1: ₹ Cr | B1: Year 1 | C1: Year 2 | D1: Year 3
A2: Acquirer net income | B2: =Assumptions!$B$4 | C2: =Assumptions!$B$4 | D2: =Assumptions!$B$4
A3: Owned target net income | B3: =(Assumptions!$B$20+26%*Assumptions!$B$36)*Assumptions!$B$13 | C3: =(Assumptions!$B$20+26%*Assumptions!$B$36)*Assumptions!$B$13 | D3: =(Assumptions!$B$20+26%*Assumptions!$B$36)*Assumptions!$B$13
A4: Synergies (phased, after-tax) | B4: =Assumptions!$B$26*Assumptions!$B$27*(1-Assumptions!$B$33) | C4: =Assumptions!$B$26*Assumptions!$B$28*(1-Assumptions!$B$33) | D4: =Assumptions!$B$26*Assumptions!$B$29*(1-Assumptions!$B$33)
A5: New interest expense (after-tax) | B5: =-'Sources & Uses'!D8*Assumptions!$B$24*(1-Assumptions!$B$33) | C5: =-'Sources & Uses'!D8*Assumptions!$B$24*(1-Assumptions!$B$33) | D5: =-'Sources & Uses'!D8*Assumptions!$B$24*(1-Assumptions!$B$33)
A6: Foregone cash yield (after-tax) | B6: =-'Sources & Uses'!D9*Assumptions!$B$25*(1-Assumptions!$B$33) | C6: =-'Sources & Uses'!D9*Assumptions!$B$25*(1-Assumptions!$B$33) | D6: =-'Sources & Uses'!D9*Assumptions!$B$25*(1-Assumptions!$B$33)
A7: Incremental D&A (after-tax) | B7: =-PPA!B8*(1-Assumptions!$B$33) | C7: =-PPA!B8*(1-Assumptions!$B$33) | D7: =-PPA!B8*(1-Assumptions!$B$33)
A8: Integration costs (after-tax, Y1) | B8: =-Assumptions!$B$30*(1-Assumptions!$B$33) | C8: =0 | D8: =0
A9: COMBINED NET INCOME | B9: =SUM(B2:B8) | C9: =SUM(C2:C8) | D9: =SUM(D2:D8)

Sheet Accretion-Dilution
A1: Item | B1: Year 1 | C1: Year 2 | D1: Year 3 | F1: Δ vs engine (Y1)
A2: Pro-forma shares (Cr) | B2: =Assumptions!$B$3+'Sources & Uses'!D12 | C2: =Assumptions!$B$3+'Sources & Uses'!D12 | D2: =Assumptions!$B$3+'Sources & Uses'!D12 | F2: =B2-454.35432901321394
A3: Pro-forma EPS (₹) | B3: ='Pro-Forma P&L'!B9/B2 | C3: ='Pro-Forma P&L'!C9/C2 | D3: ='Pro-Forma P&L'!D9/D2 | F3: =B3-57.11452647891894
A4: Standalone acquirer EPS (₹) | B4: =Assumptions!$B$4/Assumptions!$B$3 | C4: =Assumptions!$B$4/Assumptions!$B$3 | D4: =Assumptions!$B$4/Assumptions!$B$3 | F4: =B4-75.5
A5: Accretion / (dilution) | B5: =B3/B4-1 | C5: =C3/C4-1 | D5: =D3/D4-1 | F5: =B5--0.24351620557723266
A7: Break-even synergies Y1 (₹ Cr) | B7: =(B4*B2-('Pro-Forma P&L'!B9-Assumptions!$B$26*Assumptions!$B$27*(1-Assumptions!$B$33)))/(Assumptions!$B$27*(1-Assumptions!$B$33))

Sheet Regulatory
A1: Check | B1: Value | C1: Threshold | D1: Status
A2: RBI: bank debt ≤ 75% of acquisition value | B2: ='Sources & Uses'!D8/('Sources & Uses'!D2+'Sources & Uses'!D3) | C2: ≤ 75% | D2: =IF(B2<=75%,"PASS","FAIL")
A3: RBI: equity contribution ≥ 25% | B3: =1-'Sources & Uses'!D8/'Sources & Uses'!D10 | C3: ≥ 25% | D3: =IF(B3>=25%,"PASS","FAIL")
A4: RBI: pro-forma consolidated D/E ≤ 3.0x | B4: =(Assumptions!$B$7+'Sources & Uses'!D8+Assumptions!$B$16*1)/(Assumptions!$B$9+'Sources & Uses'!D7) | C4: ≤ 3.0x | D4: =IF(B4<=3,"PASS","FAIL")
A5: RBI: acquirer net worth ≥ ₹500 Cr | B5: =Assumptions!$B$9 | C5: ≥ ₹500 Cr | D5: =IF(B5>=500,"PASS","FAIL")
A7: SEBI SAST
A8: Acquiring 100% crosses the 25% threshold -> mandatory open offer for 26% of the target at the floor price (modeled at the Rs 5,526 offer price; real floor is the highest-of tests incl. 60-day VWAP).
A9: 0% acceptance: buy 0.00 Cr shares for Rs 0 Cr; post-offer holding 100.0%. BREACHES 75% MPS — must sell down within 12 months or pursue delisting (requires 90%).
A10: 50% acceptance: buy 2.03 Cr shares for Rs 11,222 Cr; post-offer holding 100.0%. BREACHES 75% MPS — must sell down within 12 months or pursue delisting (requires 90%).
A11: 100% acceptance: buy 4.06 Cr shares for Rs 22,445 Cr; post-offer holding 100.0%. BREACHES 75% MPS — must sell down within 12 months or pursue delisting (requires 90%).
A13: CCI
A14: Deal value Rs 86,327 Cr exceeds the Rs 2,000 Cr deal-value threshold (2024 amendment) — CCI approval required; expect ~150-210 days outer timeline, Green Channel possible if no overlaps.

Sheet Contribution
A1: Metric | B1: Acquirer % | C1: Target %
A2: Revenue | B2: =Assumptions!$B$5/(Assumptions!$B$5+Assumptions!$B$14) | C2: =Assumptions!$B$14/(Assumptions!$B$5+Assumptions!$B$14)
A3: EBITDA | B3: =Assumptions!$B$6/(Assumptions!$B$6+Assumptions!$B$15) | C3: =Assumptions!$B$15/(Assumptions!$B$6+Assumptions!$B$15)
A4: Net income | B4: =Assumptions!$B$4/(Assumptions!$B$4+Assumptions!$B$13) | C4: =Assumptions!$B$13/(Assumptions!$B$4+Assumptions!$B$13)
A5: Pro-forma ownership | B5: =1-'Sources & Uses'!D12/(Assumptions!$B$3+'Sources & Uses'!D12) | C5: ='Sources & Uses'!D12/(Assumptions!$B$3+'Sources & Uses'!D12)

Sheet Value Bridge
A1: Item | B1: ₹ Cr
A2: PV of after-tax synergies (perpetuity at WACC) | B2: =Assumptions!$B$26*(1-Assumptions!$B$33)/Assumptions!$B$35
A3: Control premium paid | B3: =(Assumptions!$B$19-Assumptions!$B$11)*Assumptions!$B$12*(Assumptions!$B$20+26%*Assumptions!$B$36)
A4: Net value created / (destroyed) | B4: =B2-B3
A5: Incremental NOPAT (owned NI + after-tax synergies) | B5: =(Assumptions!$B$20+26%*Assumptions!$B$36)*Assumptions!$B$13+Assumptions!$B$26*(1-Assumptions!$B$33)
A6: Invested capital (total uses) | B6: ='Sources & Uses'!D6
A7: Incremental ROIC | B7: =B5/B6
A8: WACC | B8: =Assumptions!$B$35

Sheet Sensitivity
A2: Year-1 accretion %: premium (rows) × synergies ₹ Cr (cols) — engine values
A3: Premium % \ Synergies Cr | B3: 0 | C3: 100 | D3: 200 | E3: 300 | F3: 400 | G3: 500 | H3: 600 | I3: 700 | J3: 800
A4: 8 | B4: -17.1 | C4: -16.99 | D4: -16.88 | E4: -16.77 | F4: -16.66 | G4: -16.55 | H4: -16.44 | I4: -16.33 | J4: -16.22
A5: 10.5 | B5: -17.59 | C5: -17.48 | D5: -17.37 | E5: -17.26 | F5: -17.15 | G5: -17.04 | H5: -16.93 | I5: -16.82 | J5: -16.71
A6: 13 | B6: -18.08 | C6: -17.97 | D6: -17.86 | E6: -17.75 | F6: -17.64 | G6: -17.53 | H6: -17.42 | I6: -17.31 | J6: -17.2
A7: 15.5 | B7: -18.56 | C7: -18.45 | D7: -18.34 | E7: -18.23 | F7: -18.12 | G7: -18.01 | H7: -17.9 | I7: -17.8 | J7: -17.69
A8: 18 | B8: -19.04 | C8: -18.93 | D8: -18.82 | E8: -18.72 | F8: -18.61 | G8: -18.5 | H8: -18.39 | I8: -18.28 | J8: -18.17
A9: 20.5 | B9: -19.52 | C9: -19.41 | D9: -19.31 | E9: -19.2 | F9: -19.09 | G9: -18.98 | H9: -18.87 | I9: -18.76 | J9: -18.65
A10: 23 | B10: -20 | C10: -19.89 | D10: -19.78 | E10: -19.68 | F10: -19.57 | G10: -19.46 | H10: -19.35 | I10: -19.24 | J10: -19.13
A11: 25.5 | B11: -20.48 | C11: -20.37 | D11: -20.26 | E11: -20.15 | F11: -20.04 | G11: -19.94 | H11: -19.83 | I11: -19.72 | J11: -19.61
A12: 28 | B12: -20.95 | C12: -20.84 | D12: -20.73 | E12: -20.63 | F12: -20.52 | G12: -20.41 | H12: -20.3 | I12: -20.19 | J12: -20.09
A14: Year-1 accretion %: % cash (rows) × premium (cols) — engine values
A15: % Cash \ Premium % | B15: 8 | C15: 10.5 | D15: 13 | E15: 15.5 | F15: 18 | G15: 20.5 | H15: 23 | I15: 25.5 | J15: 28
A16: 0 | B16: -17.17 | C16: -17.64 | D16: -18.1 | E16: -18.56 | F16: -19.02 | G16: -19.48 | H16: -19.93 | I16: -20.38 | J16: -20.82
A17: 10 | B17: -17.05 | C17: -17.52 | D17: -17.99 | E17: -18.46 | F17: -18.92 | G17: -19.39 | H17: -19.84 | I17: -20.3 | J17: -20.75
A18: 20 | B18: -16.92 | C18: -17.4 | D18: -17.88 | E18: -18.35 | F18: -18.82 | G18: -19.29 | H18: -19.75 | I18: -20.22 | J18: -20.68
A19: 30 | B19: -16.79 | C19: -17.28 | D19: -17.76 | E19: -18.24 | F19: -18.72 | G19: -19.19 | H19: -19.66 | I19: -20.13 | J19: -20.6
A20: 40 | B20: -16.66 | C20: -17.15 | D20: -17.64 | E20: -18.12 | F20: -18.61 | G20: -19.09 | H20: -19.57 | I20: -20.04 | J20: -20.52
A21: 50 | B21: -16.52 | C21: -17.02 | D21: -17.51 | E21: -18 | F21: -18.49 | G21: -18.98 | H21: -19.47 | I21: -19.95 | J21: -20.43
A22: 60 | B22: -16.38 | C22: -16.88 | D22: -17.38 | E22: -17.88 | F22: -18.38 | G22: -18.87 | H22: -19.36 | I22: -19.86 | J22: -20.35
A23: 70 | B23: -16.23 | C23: -16.74 | D23: -17.24 | E23: -17.75 | F23: -18.25 | G23: -18.76 | H23: -19.26 | I23: -19.76 | J23: -20.26
A24: 80 | B24: -16.08 | C24: -16.59 | D24: -17.1 | E24: -17.62 | F24: -18.13 | G24: -18.64 | H24: -19.14 | I24: -19.65 | J24: -20.16
A25: 90 | B25: -15.92 | C25: -16.44 | D25: -16.96 | E25: -17.48 | F25: -17.99 | G25: -18.51 | H25: -19.03 | I25: -19.54 | J25: -20.06
A26: 100 | B26: -15.75 | C26: -16.28 | D26: -16.81 | E26: -17.33 | F26: -17.86 | G26: -18.38 | H26: -18.91 | I26: -19.43 | J26: -19.96

Sheet Precedent Comps
A1: announce_date | B1: acquirer | C1: target | D1: deal_value_cr | E1: consideration_type | F1: offer_premium_pct | G1: ev_ebitda_multiple | H1: status | I1: notes | J1: source_url
A2: 2023-07-17 | B2: Proximus Opal | C2: Route Mobile | D2: 5922 | E2: cash | H2: completed | I2: VERIFIED — Proximus (via Proximus Opal) acquired 57.56% of Route Mobile at Rs 1626.40/sh for ~Rs 5922 cr; mandatory open offer 26% at same Rs 1626.40; completed May 2024; holding later reached ~82.7%; P/E unverified | J2: https://www.business-standard.com/companies/news/proximus-group-to-acquire-58-stake-in-route-mobile-for-rs-5-922-cr-123071700567_1.html
A3: 2019-06-18 | B3: Larsen & Toubro | C3: Mindtree | D3: 10733 | E3: cash | F3: 1.8 | H3: completed | I3: VERIFIED — hostile takeover; bought 20.3% from V.G. Siddhartha at Rs 980; open offer at Rs 980 (1.8% over Rs 962.5 mkt); raised stake to 51%; total ~Rs 10733 cr; EV/EBITDA and P/E unverified | J3: https://www.thenewsminute.com/money/lts-hostile-takeover-bid-mindtree-explained-98608
